pybraendstofpriser/__init__.py
pybraendstofpriser/companies/__init__.py
pybraendstofpriser/companies/goon.py
pybraendstofpriser/companies/oil.py
pybraendstofpriser/companies/ok.py
pybraendstofpriser/companies/q8.py
pybraendstofpriser/companies/shell.py
pybraendstofpriser/const.py
pybraendstofpriser/exceptions.py
pybraendstofpriser/tools/__init__.py
pybraendstofpriser-1.0.1.dist-info/METADATA
pybraendstofpriser-1.0.1.dist-info/WHEEL
pybraendstofpriser-1.0.1.dist-info/licenses/LICENSE
pybraendstofpriser-1.0.1.dist-info/RECORD
