Metadata-Version: 2.4
Name: pybraendstofpriser
Version: 1.0.1
Summary: Library for fetching/scraping Danish fuel prices
License: MIT
License-File: LICENSE
Author: Malene Trab
Author-email: malene@trab.dk
Requires-Python: >=3.11,<4.0
Classifier: License :: OSI Approved :: MIT License
Classifier: Programming Language :: Python :: 3
Classifier: Programming Language :: Python :: 3.11
Classifier: Programming Language :: Python :: 3.12
Classifier: Programming Language :: Python :: 3.13
Classifier: Programming Language :: Python :: 3.14
Requires-Dist: aiohttp (>=3.13.2,<4.0.0)
Requires-Dist: beautifulsoup4 (>=4.14.3,<5.0.0)
